llmadapter/__init__.py
llmadapter/base_language.py
llmadapter/cache.py
llmadapter/callbacks/__init__.py
llmadapter/callbacks/aim_callback.py
llmadapter/callbacks/argilla_callback.py
llmadapter/callbacks/arize_callback.py
llmadapter/callbacks/base.py
llmadapter/callbacks/clearml_callback.py
llmadapter/callbacks/comet_ml_callback.py
llmadapter/callbacks/human.py
llmadapter/callbacks/manager.py
llmadapter/callbacks/openai_info.py
llmadapter/callbacks/stdout.py
llmadapter/callbacks/streaming_aiter.py
llmadapter/callbacks/streaming_object.py
llmadapter/callbacks/streaming_stdout.py
llmadapter/callbacks/streaming_stdout_final_only.py
llmadapter/callbacks/streamlit.py
llmadapter/callbacks/tracers/__init__.py
llmadapter/callbacks/tracers/base.py
llmadapter/callbacks/tracers/langchain.py
llmadapter/callbacks/tracers/langchain_v1.py
llmadapter/callbacks/tracers/run_collector.py
llmadapter/callbacks/tracers/schemas.py
llmadapter/callbacks/tracers/stdout.py
llmadapter/callbacks/tracers/wandb.py
llmadapter/callbacks/utils.py
llmadapter/callbacks/wandb_callback.py
llmadapter/env.py
llmadapter/input.py
llmadapter/llms/__init__.py
llmadapter/llms/base.py
llmadapter/llms/llm_factory.py
llmadapter/llms/loading.py
llmadapter/llms/openai.py
llmadapter/llms/utils.py
llmadapter/load/__init__.py
llmadapter/load/dump.py
llmadapter/load/load.py
llmadapter/load/serializable.py
llmadapter/schema.py
llmadapter/utils.py
llmadapter-1.0.3.dist-info/METADATA
llmadapter-1.0.3.dist-info/WHEEL
llmadapter-1.0.3.dist-info/RECORD
