Metadata-Version: 2.1
Name: llmadapter
Version: 1.0.3
Summary: LLMs Adapter Package
Requires-Python: >=3.8.1,<4.0
Classifier: Programming Language :: Python :: 3
Classifier: Programming Language :: Python :: 3.9
Classifier: Programming Language :: Python :: 3.10
Classifier: Programming Language :: Python :: 3.11
Requires-Dist: PyYAML (>=5.4.1)
Requires-Dist: SQLAlchemy (>=1.4,<3)
Requires-Dist: dataclasses-json (>=0.5.7,<0.6.0)
Requires-Dist: gptcache (>=0.1.7)
Requires-Dist: langchainplus-sdk (>=0.0.9)
Requires-Dist: openai (>=0,<1)
Requires-Dist: pandas (>=2.0.1,<3.0.0)
Requires-Dist: pydantic (>=1,<2)
Requires-Dist: redis (>=4,<5)
Requires-Dist: requests (>=2,<3)
Requires-Dist: spacy (>=3,<4)
Requires-Dist: tenacity (>=8.1.0,<9.0.0)
Requires-Dist: tiktoken (>=0.3.2,<0.4.0) ; python_version >= "3.9" and python_version < "4.0"
